[
  {
    "Date": "2009-04",
    "Facebook": 13.4,
    "YouTube": 0,
    "Twitter": 5.23,
    "Pinterest": 0,
    "Instagram": 0,
    "StumbleUpon": 17.85,
    "LinkedIn": 0,
    "Tumblr": 0,
    "Google+": 0,
    "NowPublic": 0.21,
    "reddit": 3.98,
    "Digg": 34.14,
    "Delicious": 0.73,
    "VKontakte": 0,
    "Mixx": 14.74,
    "Yahoo! Buzz": 3.26,
    "news.ycombinator.com": 0.16,
    "orkut": 1.66,
    "Other": 4.63
  },
  {
    "Date": "2009-05",
    "Facebook": 14.8,
    "YouTube": 0,
    "Twitter": 6.12,
    "Pinterest": 0,
    "Instagram": 0,
    "StumbleUpon": 15.46,
    "LinkedIn": 1.43,
    "Tumblr": 0,
    "Google+": 0,
    "NowPublic": 0.25,
    "reddit": 3.19,
    "Digg": 37.11,
    "Delicious": 1.08,
    "VKontakte": 0,
    "Mixx": 12.33,
    "Yahoo! Buzz": 3.63,
    "news.ycombinator.com": 0.22,
    "orkut": 1.64,
    "Other": 2.73
  },
  {
    "Date": "2009-06",
    "Facebook": 16.06,
    "YouTube": 0,
    "Twitter": 7.37,
    "Pinterest": 0,
    "Instagram": 0,
    "StumbleUpon": 14.23,
    "LinkedIn": 2.49,
    "Tumblr": 0,
    "Google+": 0,
    "NowPublic": 0.08,
    "reddit": 7.19,
    "Digg": 41.28,
    "Delicious": 1.55,
    "VKontakte": 0,
    "Mixx": 3.74,
    "Yahoo! Buzz": 1.78,
    "news.ycombinator.com": 0.16,
    "orkut": 1.19,
    "Other": 2.88
  },
  {
    "Date": "2009-07",
    "Facebook": 19.87,
    "YouTube": 0,
    "Twitter": 17.74,
    "Pinterest": 0,
    "Instagram": 0,
    "StumbleUpon": 13,
    "LinkedIn": 1.67,
    "Tumblr": 0,
    "Google+": 0,
    "NowPublic": 0.04,
    "reddit": 4.35,
    "Digg": 31.32,
    "Delicious": 2.07,
    "VKontakte": 0,
    "Mixx": 6.19,
    "Yahoo! Buzz": 1.99,
    "news.ycombinator.com": 0.18,
    "orkut": 0.71,
    "Other": 0.86
  },
  {
    "Date": "2009-08",
    "Facebook": 23,
    "YouTube": 0,
    "Twitter": 13.08,
    "Pinterest": 0,
    "Instagram": 0,
    "StumbleUpon": 10.83,
    "LinkedIn": 2.14,
    "Tumblr": 0,
    "Google+": 0,
    "NowPublic": 0.08,
    "reddit": 3.63,
    "Digg": 36.08,
    "Delicious": 1.04,
    "VKontakte": 0,
    "Mixx": 5.68,
    "Yahoo! Buzz": 2.17,
    "news.ycombinator.com": 0.1,
    "orkut": 1.05,
    "Other": 1.11
  },
  {
    "Date": "2009-09",
    "Facebook": 27.98,
    "YouTube": 0.14,
    "Twitter": 7.19,
    "Pinterest": 0,
    "Instagram": 0,
    "StumbleUpon": 9.23,
    "LinkedIn": 2.42,
    "Tumblr": 0,
    "Google+": 0,
    "NowPublic": 0.13,
    "reddit": 2.11,
    "Digg": 38.57,
    "Delicious": 0.93,
    "VKontakte": 0,
    "Mixx": 5.72,
    "Yahoo! Buzz": 2.68,
    "news.ycombinator.com": 0.12,
    "orkut": 1.31,
    "Other": 1.47
  },
  {
    "Date": "2009-10",
    "Facebook": 24.69,
    "YouTube": 9.57,
    "Twitter": 12.48,
    "Pinterest": 0,
    "Instagram": 0,
    "StumbleUpon": 10.57,
    "LinkedIn": 2.21,
    "Tumblr": 0,
    "Google+": 0,
    "NowPublic": 0.2,
    "reddit": 2.45,
    "Digg": 28.25,
    "Delicious": 0.82,
    "VKontakte": 0,
    "Mixx": 4.82,
    "Yahoo! Buzz": 1.41,
    "news.ycombinator.com": 0.14,
    "orkut": 1.5,
    "Other": 0.88
  },
  {
    "Date": "2009-11",
    "Facebook": 34.07,
    "YouTube": 8.23,
    "Twitter": 12.91,
    "Pinterest": 0,
    "Instagram": 0,
    "StumbleUpon": 8.69,
    "LinkedIn": 1.79,
    "Tumblr": 0,
    "Google+": 0,
    "NowPublic": 0.04,
    "reddit": 1.95,
    "Digg": 17.18,
    "Delicious": 5.6,
    "VKontakte": 0,
    "Mixx": 3.76,
    "Yahoo! Buzz": 2.98,
    "news.ycombinator.com": 0.14,
    "orkut": 2.01,
    "Other": 0.66
  },
  {
    "Date": "2009-12",
    "Facebook": 54.66,
    "YouTube": 4.64,
    "Twitter": 4.56,
    "Pinterest": 0,
    "Instagram": 0,
    "StumbleUpon": 4.65,
    "LinkedIn": 1.37,
    "Tumblr": 0,
    "Google+": 0,
    "NowPublic": 0.04,
    "reddit": 1.24,
    "Digg": 12.96,
    "Delicious": 9.77,
    "VKontakte": 0,
    "Mixx": 2.62,
    "Yahoo! Buzz": 2.03,
    "news.ycombinator.com": 0.08,
    "orkut": 0.87,
    "Other": 0.52
  },
  {
    "Date": "2010-01",
    "Facebook": 52.33,
    "YouTube": 5.38,
    "Twitter": 4.97,
    "Pinterest": 0,
    "Instagram": 0,
    "StumbleUpon": 5.45,
    "LinkedIn": 1.89,
    "Tumblr": 0,
    "Google+": 0,
    "NowPublic": 0.03,
    "reddit": 1.43,
    "Digg": 13.26,
    "Delicious": 9.88,
    "VKontakte": 0,
    "Mixx": 2.11,
    "Yahoo! Buzz": 2.14,
    "news.ycombinator.com": 0.11,
    "orkut": 0.64,
    "Other": 0.38
  },
  {
    "Date": "2010-02",
    "Facebook": 47.89,
    "YouTube": 5.72,
    "Twitter": 7.54,
    "Pinterest": 0,
    "Instagram": 0,
    "StumbleUpon": 6.53,
    "LinkedIn": 2.47,
    "Tumblr": 0,
    "Google+": 0,
    "NowPublic": 3.63,
    "reddit": 1.25,
    "Digg": 10.84,
    "Delicious": 5.57,
    "VKontakte": 0,
    "Mixx": 1.81,
    "Yahoo! Buzz": 5.51,
    "news.ycombinator.com": 0.21,
    "orkut": 0.53,
    "Other": 0.5
  },
  {
    "Date": "2010-03",
    "Facebook": 44.67,
    "YouTube": 7.38,
    "Twitter": 7.55,
    "Pinterest": 0,
    "Instagram": 0,
    "StumbleUpon": 8.41,
    "LinkedIn": 3.15,
    "Tumblr": 0,
    "Google+": 0,
    "NowPublic": 8.48,
    "reddit": 1.63,
    "Digg": 8.86,
    "Delicious": 4.03,
    "VKontakte": 0,
    "Mixx": 1.47,
    "Yahoo! Buzz": 2.91,
    "news.ycombinator.com": 0.23,
    "orkut": 0.57,
    "Other": 0.66
  },
  {
    "Date": "2010-04",
    "Facebook": 64.05,
    "YouTube": 4.52,
    "Twitter": 6.69,
    "Pinterest": 0,
    "Instagram": 0,
    "StumbleUpon": 6.38,
    "LinkedIn": 1.67,
    "Tumblr": 0,
    "Google+": 0,
    "NowPublic": 3.09,
    "reddit": 0.99,
    "Digg": 5.44,
    "Delicious": 3.12,
    "VKontakte": 0,
    "Mixx": 0.98,
    "Yahoo! Buzz": 1.94,
    "news.ycombinator.com": 0.17,
    "orkut": 0.5,
    "Other": 0.48
  },
  {
    "Date": "2010-05",
    "Facebook": 65.29,
    "YouTube": 4.87,
    "Twitter": 6.38,
    "Pinterest": 0,
    "Instagram": 0,
    "StumbleUpon": 6.13,
    "LinkedIn": 1.72,
    "Tumblr": 0,
    "Google+": 0,
    "NowPublic": 2.66,
    "reddit": 1.13,
    "Digg": 5.15,
    "Delicious": 2.43,
    "VKontakte": 0,
    "Mixx": 0.85,
    "Yahoo! Buzz": 2.13,
    "news.ycombinator.com": 0.17,
    "orkut": 0.58,
    "Other": 0.51
  },
  {
    "Date": "2010-06",
    "Facebook": 73.06,
    "YouTube": 5.71,
    "Twitter": 4.88,
    "Pinterest": 0,
    "Instagram": 0,
    "StumbleUpon": 4.45,
    "LinkedIn": 1.4,
    "Tumblr": 0,
    "Google+": 0,
    "NowPublic": 2.03,
    "reddit": 0.7,
    "Digg": 4.06,
    "Delicious": 1.14,
    "VKontakte": 0,
    "Mixx": 0.46,
    "Yahoo! Buzz": 0.9,
    "news.ycombinator.com": 0.16,
    "orkut": 0.41,
    "Other": 0.65
  },
  {
    "Date": "2010-07",
    "Facebook": 77.71,
    "YouTube": 5,
    "Twitter": 5.4,
    "Pinterest": 0,
    "Instagram": 0,
    "StumbleUpon": 3.52,
    "LinkedIn": 0.81,
    "Tumblr": 0,
    "Google+": 0,
    "NowPublic": 1.57,
    "reddit": 0.57,
    "Digg": 3.13,
    "Delicious": 0.86,
    "VKontakte": 0,
    "Mixx": 0.3,
    "Yahoo! Buzz": 0.21,
    "news.ycombinator.com": 0.09,
    "orkut": 0.18,
    "Other": 0.65
  },
  {
    "Date": "2010-08",
    "Facebook": 75.25,
    "YouTube": 5.96,
    "Twitter": 6.54,
    "Pinterest": 0,
    "Instagram": 0,
    "StumbleUpon": 4.14,
    "LinkedIn": 0.91,
    "Tumblr": 0,
    "Google+": 0,
    "NowPublic": 1.6,
    "reddit": 0.61,
    "Digg": 2.78,
    "Delicious": 1,
    "VKontakte": 0,
    "Mixx": 0.42,
    "Yahoo! Buzz": 0.19,
    "news.ycombinator.com": 0.07,
    "orkut": 0.23,
    "Other": 0.31
  },
  {
    "Date": "2010-09",
    "Facebook": 75.44,
    "YouTube": 6.55,
    "Twitter": 5.54,
    "Pinterest": 0,
    "Instagram": 0,
    "StumbleUpon": 4.75,
    "LinkedIn": 1.04,
    "Tumblr": 0,
    "Google+": 0,
    "NowPublic": 2.03,
    "reddit": 0.75,
    "Digg": 1.78,
    "Delicious": 0.79,
    "VKontakte": 0,
    "Mixx": 0.46,
    "Yahoo! Buzz": 0.2,
    "news.ycombinator.com": 0.1,
    "orkut": 0.31,
    "Other": 0.25
  },
  {
    "Date": "2010-10",
    "Facebook": 79.56,
    "YouTube": 5.74,
    "Twitter": 4.39,
    "Pinterest": 0,
    "Instagram": 0,
    "StumbleUpon": 4.01,
    "LinkedIn": 0.87,
    "Tumblr": 0,
    "Google+": 0,
    "NowPublic": 1.27,
    "reddit": 0.61,
    "Digg": 1.64,
    "Delicious": 0.69,
    "VKontakte": 0,
    "Mixx": 0.4,
    "Yahoo! Buzz": 0.13,
    "news.ycombinator.com": 0.08,
    "orkut": 0.26,
    "Other": 0.36
  },
  {
    "Date": "2010-11",
    "Facebook": 80.66,
    "YouTube": 5.39,
    "Twitter": 4.01,
    "Pinterest": 0,
    "Instagram": 0,
    "StumbleUpon": 4.16,
    "LinkedIn": 0.86,
    "Tumblr": 0,
    "Google+": 0,
    "NowPublic": 1.17,
    "reddit": 0.64,
    "Digg": 1.45,
    "Delicious": 0.62,
    "VKontakte": 0,
    "Mixx": 0.32,
    "Yahoo! Buzz": 0.14,
    "news.ycombinator.com": 0.1,
    "orkut": 0.12,
    "Other": 0.36
  },
  {
    "Date": "2010-12",
    "Facebook": 80.81,
    "YouTube": 5.6,
    "Twitter": 4.22,
    "Pinterest": 0,
    "Instagram": 0,
    "StumbleUpon": 3.89,
    "LinkedIn": 0.84,
    "Tumblr": 0,
    "Google+": 0,
    "NowPublic": 1.19,
    "reddit": 0.59,
    "Digg": 1.4,
    "Delicious": 0.59,
    "VKontakte": 0,
    "Mixx": 0.28,
    "Yahoo! Buzz": 0.11,
    "news.ycombinator.com": 0.12,
    "orkut": 0.06,
    "Other": 0.3
  },
  {
    "Date": "2011-01",
    "Facebook": 83.84,
    "YouTube": 5.05,
    "Twitter": 3.49,
    "Pinterest": 0,
    "Instagram": 0,
    "StumbleUpon": 3.2,
    "LinkedIn": 0.71,
    "Tumblr": 0,
    "Google+": 0,
    "NowPublic": 0.98,
    "reddit": 0.51,
    "Digg": 1.15,
    "Delicious": 0.37,
    "VKontakte": 0,
    "Mixx": 0.26,
    "Yahoo! Buzz": 0.1,
    "news.ycombinator.com": 0.08,
    "orkut": 0.04,
    "Other": 0.23
  },
  {
    "Date": "2011-02",
    "Facebook": 82.31,
    "YouTube": 5.83,
    "Twitter": 3.53,
    "Pinterest": 0,
    "Instagram": 0,
    "StumbleUpon": 3.64,
    "LinkedIn": 0.79,
    "Tumblr": 0,
    "Google+": 0,
    "NowPublic": 1.29,
    "reddit": 0.45,
    "Digg": 1.13,
    "Delicious": 0.29,
    "VKontakte": 0,
    "Mixx": 0.27,
    "Yahoo! Buzz": 0.12,
    "news.ycombinator.com": 0.08,
    "orkut": 0.05,
    "Other": 0.22
  },
  {
    "Date": "2011-03",
    "Facebook": 88.01,
    "YouTube": 3.07,
    "Twitter": 2.99,
    "Pinterest": 0,
    "Instagram": 0,
    "StumbleUpon": 2.58,
    "LinkedIn": 0.5,
    "Tumblr": 0,
    "Google+": 0,
    "NowPublic": 1.1,
    "reddit": 0.3,
    "Digg": 0.72,
    "Delicious": 0.18,
    "VKontakte": 0,
    "Mixx": 0.22,
    "Yahoo! Buzz": 0.09,
    "news.ycombinator.com": 0.05,
    "orkut": 0.05,
    "Other": 0.13
  },
  {
    "Date": "2011-04",
    "Facebook": 92.27,
    "YouTube": 2.2,
    "Twitter": 1.6,
    "Pinterest": 0,
    "Instagram": 0,
    "StumbleUpon": 1.91,
    "LinkedIn": 0.42,
    "Tumblr": 0,
    "Google+": 0,
    "NowPublic": 0.49,
    "reddit": 0.17,
    "Digg": 0.56,
    "Delicious": 0.1,
    "VKontakte": 0,
    "Mixx": 0.1,
    "Yahoo! Buzz": 0.03,
    "news.ycombinator.com": 0.04,
    "orkut": 0.03,
    "Other": 0.08
  },
  {
    "Date": "2011-05",
    "Facebook": 88.74,
    "YouTube": 3,
    "Twitter": 1.79,
    "Pinterest": 0,
    "Instagram": 0,
    "StumbleUpon": 2.54,
    "LinkedIn": 0.63,
    "Tumblr": 0,
    "Google+": 0,
    "NowPublic": 2.23,
    "reddit": 0.22,
    "Digg": 0.55,
    "Delicious": 0.12,
    "VKontakte": 0,
    "Mixx": 0,
    "Yahoo! Buzz": 0,
    "news.ycombinator.com": 0.05,
    "orkut": 0.03,
    "Other": 0.11
  },
  {
    "Date": "2011-06",
    "Facebook": 86.62,
    "YouTube": 3.46,
    "Twitter": 2.1,
    "Pinterest": 0,
    "Instagram": 0,
    "StumbleUpon": 3.07,
    "LinkedIn": 1.1,
    "Tumblr": 0,
    "Google+": 0,
    "NowPublic": 2.55,
    "reddit": 0.24,
    "Digg": 0.52,
    "Delicious": 0.08,
    "VKontakte": 0,
    "Mixx": 0,
    "Yahoo! Buzz": 0,
    "news.ycombinator.com": 0.07,
    "orkut": 0.03,
    "Other": 0.17
  },
  {
    "Date": "2011-07",
    "Facebook": 82.69,
    "YouTube": 4.77,
    "Twitter": 2.51,
    "Pinterest": 0,
    "Instagram": 0,
    "StumbleUpon": 4.58,
    "LinkedIn": 1.55,
    "Tumblr": 0,
    "Google+": 0.59,
    "NowPublic": 2.1,
    "reddit": 0.35,
    "Digg": 0.52,
    "Delicious": 0.08,
    "VKontakte": 0,
    "Mixx": 0,
    "Yahoo! Buzz": 0,
    "news.ycombinator.com": 0.08,
    "orkut": 0.08,
    "Other": 0.11
  },
  {
    "Date": "2011-08",
    "Facebook": 84.22,
    "YouTube": 4.83,
    "Twitter": 2.24,
    "Pinterest": 0,
    "Instagram": 0,
    "StumbleUpon": 4.89,
    "LinkedIn": 1.15,
    "Tumblr": 0,
    "Google+": 0.29,
    "NowPublic": 1.34,
    "reddit": 0.3,
    "Digg": 0.43,
    "Delicious": 0.08,
    "VKontakte": 0,
    "Mixx": 0,
    "Yahoo! Buzz": 0,
    "news.ycombinator.com": 0.08,
    "orkut": 0.08,
    "Other": 0.07
  },
  {
    "Date": "2011-09",
    "Facebook": 84.58,
    "YouTube": 3.55,
    "Twitter": 3.85,
    "Pinterest": 0,
    "Instagram": 0,
    "StumbleUpon": 4.56,
    "LinkedIn": 1.04,
    "Tumblr": 0,
    "Google+": 0.18,
    "NowPublic": 1.14,
    "reddit": 0.36,
    "Digg": 0.4,
    "Delicious": 0.08,
    "VKontakte": 0,
    "Mixx": 0,
    "Yahoo! Buzz": 0,
    "news.ycombinator.com": 0.05,
    "orkut": 0.07,
    "Other": 0.14
  },
  {
    "Date": "2011-10",
    "Facebook": 80.23,
    "YouTube": 4.65,
    "Twitter": 4.95,
    "Pinterest": 0,
    "Instagram": 0,
    "StumbleUpon": 5.91,
    "LinkedIn": 1.34,
    "Tumblr": 0,
    "Google+": 0.17,
    "NowPublic": 1.17,
    "reddit": 0.54,
    "Digg": 0.63,
    "Delicious": 0.05,
    "VKontakte": 0,
    "Mixx": 0,
    "Yahoo! Buzz": 0,
    "news.ycombinator.com": 0.15,
    "orkut": 0.08,
    "Other": 0.11
  },
  {
    "Date": "2011-11",
    "Facebook": 83.82,
    "YouTube": 3.17,
    "Twitter": 4.37,
    "Pinterest": 0,
    "Instagram": 0,
    "StumbleUpon": 5.06,
    "LinkedIn": 0.93,
    "Tumblr": 0,
    "Google+": 0.16,
    "NowPublic": 1.13,
    "reddit": 0.39,
    "Digg": 0.68,
    "Delicious": 0.05,
    "VKontakte": 0,
    "Mixx": 0,
    "Yahoo! Buzz": 0,
    "news.ycombinator.com": 0.08,
    "orkut": 0.06,
    "Other": 0.1
  },
  {
    "Date": "2011-12",
    "Facebook": 89.58,
    "YouTube": 2.45,
    "Twitter": 3.07,
    "Pinterest": 0,
    "Instagram": 0,
    "StumbleUpon": 2.33,
    "LinkedIn": 0.71,
    "Tumblr": 0,
    "Google+": 0.02,
    "NowPublic": 0.9,
    "reddit": 0.32,
    "Digg": 0.4,
    "Delicious": 0.02,
    "VKontakte": 0,
    "Mixx": 0,
    "Yahoo! Buzz": 0,
    "news.ycombinator.com": 0.09,
    "orkut": 0.05,
    "Other": 0.05
  },
  {
    "Date": "2012-01",
    "Facebook": 89.99,
    "YouTube": 2.5,
    "Twitter": 3.06,
    "Pinterest": 0,
    "Instagram": 0,
    "StumbleUpon": 2.03,
    "LinkedIn": 0.85,
    "Tumblr": 0,
    "Google+": 0,
    "NowPublic": 0.58,
    "reddit": 0.34,
    "Digg": 0.46,
    "Delicious": 0.02,
    "VKontakte": 0,
    "Mixx": 0,
    "Yahoo! Buzz": 0,
    "news.ycombinator.com": 0.07,
    "orkut": 0.05,
    "Other": 0.05
  },
  {
    "Date": "2012-02",
    "Facebook": 84.31,
    "YouTube": 9.13,
    "Twitter": 2.58,
    "Pinterest": 0,
    "Instagram": 0,
    "StumbleUpon": 1.58,
    "LinkedIn": 0.99,
    "Tumblr": 0,
    "Google+": 0.02,
    "NowPublic": 0.45,
    "reddit": 0.35,
    "Digg": 0.38,
    "Delicious": 0.02,
    "VKontakte": 0.01,
    "Mixx": 0,
    "Yahoo! Buzz": 0,
    "news.ycombinator.com": 0.06,
    "orkut": 0.05,
    "Other": 0.06
  },
  {
    "Date": "2012-03",
    "Facebook": 72.85,
    "YouTube": 23.98,
    "Twitter": 0.94,
    "Pinterest": 0.04,
    "Instagram": 0,
    "StumbleUpon": 0.43,
    "LinkedIn": 0.99,
    "Tumblr": 0,
    "Google+": 0.05,
    "NowPublic": 0.17,
    "reddit": 0.14,
    "Digg": 0.12,
    "Delicious": 0.01,
    "VKontakte": 0.02,
    "Mixx": 0,
    "Yahoo! Buzz": 0,
    "news.ycombinator.com": 0.02,
    "orkut": 0.1,
    "Other": 0.15
  },
  {
    "Date": "2012-04",
    "Facebook": 72.28,
    "YouTube": 22.97,
    "Twitter": 1.43,
    "Pinterest": 0.13,
    "Instagram": 0,
    "StumbleUpon": 0.87,
    "LinkedIn": 1.25,
    "Tumblr": 0,
    "Google+": 0.05,
    "NowPublic": 0.41,
    "reddit": 0.12,
    "Digg": 0.21,
    "Delicious": 0.01,
    "VKontakte": 0.01,
    "Mixx": 0,
    "Yahoo! Buzz": 0,
    "news.ycombinator.com": 0.03,
    "orkut": 0.09,
    "Other": 0.16
  },
  {
    "Date": "2012-05",
    "Facebook": 71.29,
    "YouTube": 21.92,
    "Twitter": 1.99,
    "Pinterest": 0.2,
    "Instagram": 0,
    "StumbleUpon": 1.08,
    "LinkedIn": 1.41,
    "Tumblr": 0,
    "Google+": 0.04,
    "NowPublic": 1.31,
    "reddit": 0.18,
    "Digg": 0.29,
    "Delicious": 0.01,
    "VKontakte": 0.01,
    "Mixx": 0,
    "Yahoo! Buzz": 0,
    "news.ycombinator.com": 0.03,
    "orkut": 0.08,
    "Other": 0.17
  },
  {
    "Date": "2012-06",
    "Facebook": 73.82,
    "YouTube": 18.58,
    "Twitter": 2.1,
    "Pinterest": 0.27,
    "Instagram": 0,
    "StumbleUpon": 1.23,
    "LinkedIn": 1.39,
    "Tumblr": 0,
    "Google+": 0.04,
    "NowPublic": 1.68,
    "reddit": 0.21,
    "Digg": 0.36,
    "Delicious": 0.01,
    "VKontakte": 0.01,
    "Mixx": 0,
    "Yahoo! Buzz": 0,
    "news.ycombinator.com": 0.05,
    "orkut": 0.06,
    "Other": 0.19
  },
  {
    "Date": "2012-07",
    "Facebook": 79.72,
    "YouTube": 9.06,
    "Twitter": 3.31,
    "Pinterest": 0.54,
    "Instagram": 0,
    "StumbleUpon": 2.28,
    "LinkedIn": 1.36,
    "Tumblr": 0,
    "Google+": 0.01,
    "NowPublic": 2.38,
    "reddit": 0.39,
    "Digg": 0.64,
    "Delicious": 0.02,
    "VKontakte": 0,
    "Mixx": 0,
    "Yahoo! Buzz": 0,
    "news.ycombinator.com": 0.08,
    "orkut": 0.03,
    "Other": 0.17
  },
  {
    "Date": "2012-08",
    "Facebook": 80.72,
    "YouTube": 6.73,
    "Twitter": 4.14,
    "Pinterest": 0.83,
    "Instagram": 0,
    "StumbleUpon": 2.75,
    "LinkedIn": 1.46,
    "Tumblr": 0,
    "Google+": 0,
    "NowPublic": 2.53,
    "reddit": 0.46,
    "Digg": 0.03,
    "Delicious": 0.02,
    "VKontakte": 0,
    "Mixx": 0,
    "Yahoo! Buzz": 0,
    "news.ycombinator.com": 0.17,
    "orkut": 0.02,
    "Other": 0.12
  },
  {
    "Date": "2012-09",
    "Facebook": 76.59,
    "YouTube": 8.49,
    "Twitter": 4.29,
    "Pinterest": 1.01,
    "Instagram": 0,
    "StumbleUpon": 3.14,
    "LinkedIn": 1.81,
    "Tumblr": 0,
    "Google+": 0,
    "NowPublic": 3.91,
    "reddit": 0.49,
    "Digg": 0.03,
    "Delicious": 0.02,
    "VKontakte": 0,
    "Mixx": 0,
    "Yahoo! Buzz": 0,
    "news.ycombinator.com": 0.09,
    "orkut": 0.02,
    "Other": 0.1
  },
  {
    "Date": "2012-10",
    "Facebook": 77.77,
    "YouTube": 8.3,
    "Twitter": 5.14,
    "Pinterest": 1.15,
    "Instagram": 0,
    "StumbleUpon": 2.75,
    "LinkedIn": 1.48,
    "Tumblr": 0,
    "Google+": 0,
    "NowPublic": 2.58,
    "reddit": 0.52,
    "Digg": 0.03,
    "Delicious": 0.03,
    "VKontakte": 0,
    "Mixx": 0,
    "Yahoo! Buzz": 0,
    "news.ycombinator.com": 0.11,
    "orkut": 0.02,
    "Other": 0.12
  },
  {
    "Date": "2012-11",
    "Facebook": 79.11,
    "YouTube": 6.35,
    "Twitter": 5.45,
    "Pinterest": 1.34,
    "Instagram": 0,
    "StumbleUpon": 2.43,
    "LinkedIn": 1.78,
    "Tumblr": 0,
    "Google+": 0,
    "NowPublic": 2.52,
    "reddit": 0.58,
    "Digg": 0.01,
    "Delicious": 0.02,
    "VKontakte": 0,
    "Mixx": 0,
    "Yahoo! Buzz": 0,
    "news.ycombinator.com": 0.17,
    "orkut": 0.02,
    "Other": 0.21
  },
  {
    "Date": "2012-12",
    "Facebook": 80.24,
    "YouTube": 5.25,
    "Twitter": 5.93,
    "Pinterest": 1.46,
    "Instagram": 0,
    "StumbleUpon": 2.23,
    "LinkedIn": 1.7,
    "Tumblr": 0,
    "Google+": 0,
    "NowPublic": 2.35,
    "reddit": 0.5,
    "Digg": 0.02,
    "Delicious": 0.02,
    "VKontakte": 0.01,
    "Mixx": 0,
    "Yahoo! Buzz": 0,
    "news.ycombinator.com": 0.19,
    "orkut": 0.02,
    "Other": 0.08
  },
  {
    "Date": "2013-01",
    "Facebook": 78.35,
    "YouTube": 6.1,
    "Twitter": 6.95,
    "Pinterest": 1.6,
    "Instagram": 0,
    "StumbleUpon": 2.41,
    "LinkedIn": 1.57,
    "Tumblr": 0,
    "Google+": 0.01,
    "NowPublic": 2.28,
    "reddit": 0.48,
    "Digg": 0.02,
    "Delicious": 0.01,
    "VKontakte": 0.01,
    "Mixx": 0,
    "Yahoo! Buzz": 0,
    "news.ycombinator.com": 0.12,
    "orkut": 0.02,
    "Other": 0.07
  },
  {
    "Date": "2013-02",
    "Facebook": 79.4,
    "YouTube": 5.75,
    "Twitter": 6.09,
    "Pinterest": 1.62,
    "Instagram": 0,
    "StumbleUpon": 2.39,
    "LinkedIn": 1.5,
    "Tumblr": 0,
    "Google+": 0.61,
    "NowPublic": 1.97,
    "reddit": 0.45,
    "Digg": 0.01,
    "Delicious": 0,
    "VKontakte": 0.01,
    "Mixx": 0,
    "Yahoo! Buzz": 0,
    "news.ycombinator.com": 0.13,
    "orkut": 0.02,
    "Other": 0.06
  },
  {
    "Date": "2013-03",
    "Facebook": 76.49,
    "YouTube": 7.14,
    "Twitter": 6.75,
    "Pinterest": 1.7,
    "Instagram": 0,
    "StumbleUpon": 2.79,
    "LinkedIn": 1.31,
    "Tumblr": 0,
    "Google+": 0.7,
    "NowPublic": 2.52,
    "reddit": 0.46,
    "Digg": 0.02,
    "Delicious": 0,
    "VKontakte": 0.01,
    "Mixx": 0,
    "Yahoo! Buzz": 0,
    "news.ycombinator.com": 0.04,
    "orkut": 0.01,
    "Other": 0.07
  },
  {
    "Date": "2013-04",
    "Facebook": 78.38,
    "YouTube": 4.91,
    "Twitter": 6.94,
    "Pinterest": 1.76,
    "Instagram": 0,
    "StumbleUpon": 3.08,
    "LinkedIn": 1.26,
    "Tumblr": 0,
    "Google+": 0.72,
    "NowPublic": 2.3,
    "reddit": 0.52,
    "Digg": 0.04,
    "Delicious": 0.01,
    "VKontakte": 0,
    "Mixx": 0,
    "Yahoo! Buzz": 0,
    "news.ycombinator.com": 0,
    "orkut": 0.01,
    "Other": 0.07
  },
  {
    "Date": "2013-05",
    "Facebook": 81.44,
    "YouTube": 4,
    "Twitter": 5.63,
    "Pinterest": 1.55,
    "Instagram": 0,
    "StumbleUpon": 3.01,
    "LinkedIn": 1.11,
    "Tumblr": 0,
    "Google+": 0.6,
    "NowPublic": 1.97,
    "reddit": 0.57,
    "Digg": 0.02,
    "Delicious": 0,
    "VKontakte": 0.03,
    "Mixx": 0,
    "Yahoo! Buzz": 0,
    "news.ycombinator.com": 0,
    "orkut": 0.01,
    "Other": 0.06
  },
  {
    "Date": "2013-06",
    "Facebook": 81.69,
    "YouTube": 3.8,
    "Twitter": 5.13,
    "Pinterest": 1.28,
    "Instagram": 0,
    "StumbleUpon": 2.46,
    "LinkedIn": 0.92,
    "Tumblr": 0,
    "Google+": 0.58,
    "NowPublic": 3.56,
    "reddit": 0.44,
    "Digg": 0.02,
    "Delicious": 0,
    "VKontakte": 0.05,
    "Mixx": 0,
    "Yahoo! Buzz": 0,
    "news.ycombinator.com": 0,
    "orkut": 0.01,
    "Other": 0.05
  },
  {
    "Date": "2013-07",
    "Facebook": 78.03,
    "YouTube": 5.34,
    "Twitter": 6.11,
    "Pinterest": 1.54,
    "Instagram": 0,
    "StumbleUpon": 3.08,
    "LinkedIn": 1.04,
    "Tumblr": 0,
    "Google+": 0.63,
    "NowPublic": 3.72,
    "reddit": 0.42,
    "Digg": 0.02,
    "Delicious": 0.01,
    "VKontakte": 0.01,
    "Mixx": 0,
    "Yahoo! Buzz": 0,
    "news.ycombinator.com": 0,
    "orkut": 0.01,
    "Other": 0.04
  },
  {
    "Date": "2013-08",
    "Facebook": 81.03,
    "YouTube": 5.04,
    "Twitter": 6,
    "Pinterest": 1.45,
    "Instagram": 0,
    "StumbleUpon": 3.13,
    "LinkedIn": 1.14,
    "Tumblr": 0,
    "Google+": 0.63,
    "NowPublic": 1.07,
    "reddit": 0.39,
    "Digg": 0.03,
    "Delicious": 0,
    "VKontakte": 0.01,
    "Mixx": 0,
    "Yahoo! Buzz": 0,
    "news.ycombinator.com": 0,
    "orkut": 0.01,
    "Other": 0.05
  },
  {
    "Date": "2013-09",
    "Facebook": 81.84,
    "YouTube": 4.34,
    "Twitter": 6.2,
    "Pinterest": 1.52,
    "Instagram": 0,
    "StumbleUpon": 2.8,
    "LinkedIn": 1.02,
    "Tumblr": 0,
    "Google+": 0.64,
    "NowPublic": 1.08,
    "reddit": 0.45,
    "Digg": 0.03,
    "Delicious": 0,
    "VKontakte": 0.01,
    "Mixx": 0,
    "Yahoo! Buzz": 0,
    "news.ycombinator.com": 0,
    "orkut": 0.01,
    "Other": 0.05
  },
  {
    "Date": "2013-10",
    "Facebook": 84.57,
    "YouTube": 3.47,
    "Twitter": 4.91,
    "Pinterest": 1.09,
    "Instagram": 0,
    "StumbleUpon": 2.34,
    "LinkedIn": 0.8,
    "Tumblr": 0.3,
    "Google+": 0.6,
    "NowPublic": 1.49,
    "reddit": 0.34,
    "Digg": 0.02,
    "Delicious": 0,
    "VKontakte": 0.01,
    "Mixx": 0,
    "Yahoo! Buzz": 0,
    "news.ycombinator.com": 0,
    "orkut": 0,
    "Other": 0.04
  },
  {
    "Date": "2013-11",
    "Facebook": 85.57,
    "YouTube": 3.44,
    "Twitter": 4.19,
    "Pinterest": 0.98,
    "Instagram": 0,
    "StumbleUpon": 1.99,
    "LinkedIn": 0.57,
    "Tumblr": 2.24,
    "Google+": 0.54,
    "NowPublic": 0.14,
    "reddit": 0.28,
    "Digg": 0.02,
    "Delicious": 0,
    "VKontakte": 0.01,
    "Mixx": 0,
    "Yahoo! Buzz": 0,
    "news.ycombinator.com": 0,
    "orkut": 0,
    "Other": 0.04
  },
  {
    "Date": "2013-12",
    "Facebook": 79.54,
    "YouTube": 7.23,
    "Twitter": 4.92,
    "Pinterest": 1.3,
    "Instagram": 0,
    "StumbleUpon": 2.24,
    "LinkedIn": 0.68,
    "Tumblr": 2.83,
    "Google+": 0.63,
    "NowPublic": 0.16,
    "reddit": 0.34,
    "Digg": 0.03,
    "Delicious": 0,
    "VKontakte": 0.01,
    "Mixx": 0,
    "Yahoo! Buzz": 0,
    "news.ycombinator.com": 0,
    "orkut": 0,
    "Other": 0.08
  },
  {
    "Date": "2014-01",
    "Facebook": 78.99,
    "YouTube": 8.12,
    "Twitter": 4.71,
    "Pinterest": 1.37,
    "Instagram": 0,
    "StumbleUpon": 2.03,
    "LinkedIn": 0.64,
    "Tumblr": 2.95,
    "Google+": 0.68,
    "NowPublic": 0,
    "reddit": 0.42,
    "Digg": 0.02,
    "Delicious": 0,
    "VKontakte": 0.01,
    "Mixx": 0,
    "Yahoo! Buzz": 0,
    "news.ycombinator.com": 0,
    "orkut": 0,
    "Other": 0.07
  },
  {
    "Date": "2014-02",
    "Facebook": 79.69,
    "YouTube": 6.77,
    "Twitter": 3.94,
    "Pinterest": 1.58,
    "Instagram": 0,
    "StumbleUpon": 2.07,
    "LinkedIn": 0.65,
    "Tumblr": 3.47,
    "Google+": 0.63,
    "NowPublic": 0,
    "reddit": 1.11,
    "Digg": 0.02,
    "Delicious": 0,
    "VKontakte": 0.01,
    "Mixx": 0,
    "Yahoo! Buzz": 0,
    "news.ycombinator.com": 0,
    "orkut": 0,
    "Other": 0.04
  },
  {
    "Date": "2014-03",
    "Facebook": 80.06,
    "YouTube": 7.42,
    "Twitter": 4.02,
    "Pinterest": 1.8,
    "Instagram": 0,
    "StumbleUpon": 2.01,
    "LinkedIn": 0.62,
    "Tumblr": 2.81,
    "Google+": 0.7,
    "NowPublic": 0,
    "reddit": 0.49,
    "Digg": 0.02,
    "Delicious": 0,
    "VKontakte": 0.01,
    "Mixx": 0,
    "Yahoo! Buzz": 0,
    "news.ycombinator.com": 0,
    "orkut": 0,
    "Other": 0.04
  },
  {
    "Date": "2014-04",
    "Facebook": 80.86,
    "YouTube": 5.93,
    "Twitter": 4.32,
    "Pinterest": 1.84,
    "Instagram": 0,
    "StumbleUpon": 2.44,
    "LinkedIn": 0.67,
    "Tumblr": 2.74,
    "Google+": 0.71,
    "NowPublic": 0,
    "reddit": 0.42,
    "Digg": 0.01,
    "Delicious": 0,
    "VKontakte": 0.01,
    "Mixx": 0,
    "Yahoo! Buzz": 0,
    "news.ycombinator.com": 0,
    "orkut": 0,
    "Other": 0.05
  },
  {
    "Date": "2014-05",
    "Facebook": 81.2,
    "YouTube": 5.79,
    "Twitter": 4.4,
    "Pinterest": 2.03,
    "Instagram": 0,
    "StumbleUpon": 2.58,
    "LinkedIn": 0.55,
    "Tumblr": 2.23,
    "Google+": 0.66,
    "NowPublic": 0,
    "reddit": 0.48,
    "Digg": 0.01,
    "Delicious": 0,
    "VKontakte": 0.01,
    "Mixx": 0,
    "Yahoo! Buzz": 0,
    "news.ycombinator.com": 0,
    "orkut": 0,
    "Other": 0.05
  },
  {
    "Date": "2014-06",
    "Facebook": 81.05,
    "YouTube": 6.66,
    "Twitter": 3.96,
    "Pinterest": 1.86,
    "Instagram": 0,
    "StumbleUpon": 1.99,
    "LinkedIn": 0.22,
    "Tumblr": 3.15,
    "Google+": 0.61,
    "NowPublic": 0,
    "reddit": 0.42,
    "Digg": 0.01,
    "Delicious": 0.01,
    "VKontakte": 0.01,
    "Mixx": 0,
    "Yahoo! Buzz": 0,
    "news.ycombinator.com": 0,
    "orkut": 0,
    "Other": 0.06
  },
  {
    "Date": "2014-07",
    "Facebook": 88.16,
    "YouTube": 2.85,
    "Twitter": 3.25,
    "Pinterest": 1.46,
    "Instagram": 0,
    "StumbleUpon": 1.13,
    "LinkedIn": 0.31,
    "Tumblr": 1.95,
    "Google+": 0.49,
    "NowPublic": 0,
    "reddit": 0.29,
    "Digg": 0.01,
    "Delicious": 0,
    "VKontakte": 0.03,
    "Mixx": 0,
    "Yahoo! Buzz": 0,
    "news.ycombinator.com": 0.02,
    "orkut": 0,
    "Other": 0.05
  },
  {
    "Date": "2014-08",
    "Facebook": 92.13,
    "YouTube": 0.69,
    "Twitter": 2.68,
    "Pinterest": 1.19,
    "Instagram": 0,
    "StumbleUpon": 1.04,
    "LinkedIn": 0.25,
    "Tumblr": 1.28,
    "Google+": 0.39,
    "NowPublic": 0,
    "reddit": 0.25,
    "Digg": 0,
    "Delicious": 0,
    "VKontakte": 0.02,
    "Mixx": 0,
    "Yahoo! Buzz": 0,
    "news.ycombinator.com": 0.02,
    "orkut": 0,
    "Other": 0.04
  },
  {
    "Date": "2014-09",
    "Facebook": 94.14,
    "YouTube": 0.42,
    "Twitter": 2.17,
    "Pinterest": 0.93,
    "Instagram": 0,
    "StumbleUpon": 0.67,
    "LinkedIn": 0.21,
    "Tumblr": 0.75,
    "Google+": 0.33,
    "NowPublic": 0,
    "reddit": 0.32,
    "Digg": 0,
    "Delicious": 0,
    "VKontakte": 0.01,
    "Mixx": 0,
    "Yahoo! Buzz": 0,
    "news.ycombinator.com": 0.01,
    "orkut": 0,
    "Other": 0.02
  },
  {
    "Date": "2014-10",
    "Facebook": 94.58,
    "YouTube": 0.48,
    "Twitter": 2.05,
    "Pinterest": 0.85,
    "Instagram": 0,
    "StumbleUpon": 0.6,
    "LinkedIn": 0.17,
    "Tumblr": 0.67,
    "Google+": 0.36,
    "NowPublic": 0,
    "reddit": 0.19,
    "Digg": 0,
    "Delicious": 0,
    "VKontakte": 0.02,
    "Mixx": 0,
    "Yahoo! Buzz": 0,
    "news.ycombinator.com": 0.01,
    "orkut": 0,
    "Other": 0.02
  },
  {
    "Date": "2014-11",
    "Facebook": 94.73,
    "YouTube": 0.4,
    "Twitter": 1.65,
    "Pinterest": 0.91,
    "Instagram": 0,
    "StumbleUpon": 0.63,
    "LinkedIn": 0.16,
    "Tumblr": 0.61,
    "Google+": 0.4,
    "NowPublic": 0,
    "reddit": 0.45,
    "Digg": 0,
    "Delicious": 0,
    "VKontakte": 0.03,
    "Mixx": 0,
    "Yahoo! Buzz": 0,
    "news.ycombinator.com": 0.02,
    "orkut": 0,
    "Other": 0.01
  },
  {
    "Date": "2014-12",
    "Facebook": 95.64,
    "YouTube": 0.13,
    "Twitter": 1.5,
    "Pinterest": 0.85,
    "Instagram": 0,
    "StumbleUpon": 0.59,
    "LinkedIn": 0.14,
    "Tumblr": 0.53,
    "Google+": 0.4,
    "NowPublic": 0,
    "reddit": 0.18,
    "Digg": 0,
    "Delicious": 0,
    "VKontakte": 0.02,
    "Mixx": 0,
    "Yahoo! Buzz": 0,
    "news.ycombinator.com": 0.02,
    "orkut": 0,
    "Other": 0.01
  },
  {
    "Date": "2015-01",
    "Facebook": 95.67,
    "YouTube": 0.11,
    "Twitter": 1.58,
    "Pinterest": 0.84,
    "Instagram": 0,
    "StumbleUpon": 0.57,
    "LinkedIn": 0.13,
    "Tumblr": 0.49,
    "Google+": 0.39,
    "NowPublic": 0,
    "reddit": 0.16,
    "Digg": 0.01,
    "Delicious": 0,
    "VKontakte": 0.02,
    "Mixx": 0,
    "Yahoo! Buzz": 0,
    "news.ycombinator.com": 0.02,
    "orkut": 0,
    "Other": 0.01
  },
  {
    "Date": "2015-02",
    "Facebook": 95.19,
    "YouTube": 0.11,
    "Twitter": 1.74,
    "Pinterest": 0.85,
    "Instagram": 0,
    "StumbleUpon": 0.63,
    "LinkedIn": 0.15,
    "Tumblr": 0.52,
    "Google+": 0.57,
    "NowPublic": 0,
    "reddit": 0.18,
    "Digg": 0,
    "Delicious": 0,
    "VKontakte": 0.02,
    "Mixx": 0,
    "Yahoo! Buzz": 0,
    "news.ycombinator.com": 0.01,
    "orkut": 0,
    "Other": 0.01
  },
  {
    "Date": "2015-03",
    "Facebook": 95.44,
    "YouTube": 0.14,
    "Twitter": 1.48,
    "Pinterest": 0.8,
    "Instagram": 0,
    "StumbleUpon": 0.54,
    "LinkedIn": 0.12,
    "Tumblr": 0.59,
    "Google+": 0.66,
    "NowPublic": 0,
    "reddit": 0.2,
    "Digg": 0,
    "Delicious": 0,
    "VKontakte": 0.02,
    "Mixx": 0,
    "Yahoo! Buzz": 0,
    "news.ycombinator.com": 0.01,
    "orkut": 0,
    "Other": 0
  },
  {
    "Date": "2015-04",
    "Facebook": 95.53,
    "YouTube": 0.1,
    "Twitter": 1.59,
    "Pinterest": 0.78,
    "Instagram": 0,
    "StumbleUpon": 0.56,
    "LinkedIn": 0.12,
    "Tumblr": 0.56,
    "Google+": 0.53,
    "NowPublic": 0,
    "reddit": 0.18,
    "Digg": 0,
    "Delicious": 0,
    "VKontakte": 0.02,
    "Mixx": 0,
    "Yahoo! Buzz": 0,
    "news.ycombinator.com": 0.02,
    "orkut": 0,
    "Other": 0.02
  },
  {
    "Date": "2015-05",
    "Facebook": 95.65,
    "YouTube": 0.1,
    "Twitter": 1.51,
    "Pinterest": 0.79,
    "Instagram": 0,
    "StumbleUpon": 0.54,
    "LinkedIn": 0.12,
    "Tumblr": 0.54,
    "Google+": 0.54,
    "NowPublic": 0,
    "reddit": 0.16,
    "Digg": 0,
    "Delicious": 0,
    "VKontakte": 0.01,
    "Mixx": 0,
    "Yahoo! Buzz": 0,
    "news.ycombinator.com": 0.02,
    "orkut": 0,
    "Other": 0
  },
  {
    "Date": "2015-06",
    "Facebook": 95.97,
    "YouTube": 0.09,
    "Twitter": 1.36,
    "Pinterest": 0.83,
    "Instagram": 0,
    "StumbleUpon": 0.51,
    "LinkedIn": 0.14,
    "Tumblr": 0.5,
    "Google+": 0.43,
    "NowPublic": 0,
    "reddit": 0.14,
    "Digg": 0,
    "Delicious": 0,
    "VKontakte": 0.01,
    "Mixx": 0,
    "Yahoo! Buzz": 0,
    "news.ycombinator.com": 0.01,
    "orkut": 0,
    "Other": 0
  },
  {
    "Date": "2015-07",
    "Facebook": 96.06,
    "YouTube": 0.09,
    "Twitter": 1.4,
    "Pinterest": 0.82,
    "Instagram": 0,
    "StumbleUpon": 0.44,
    "LinkedIn": 0.14,
    "Tumblr": 0.47,
    "Google+": 0.39,
    "NowPublic": 0,
    "reddit": 0.16,
    "Digg": 0,
    "Delicious": 0,
    "VKontakte": 0.01,
    "Mixx": 0,
    "Yahoo! Buzz": 0,
    "news.ycombinator.com": 0.01,
    "orkut": 0,
    "Other": 0
  },
  {
    "Date": "2015-08",
    "Facebook": 94.35,
    "YouTube": 0.22,
    "Twitter": 1.81,
    "Pinterest": 1.16,
    "Instagram": 0,
    "StumbleUpon": 0.6,
    "LinkedIn": 0.28,
    "Tumblr": 0.61,
    "Google+": 0.58,
    "NowPublic": 0,
    "reddit": 0.36,
    "Digg": 0,
    "Delicious": 0,
    "VKontakte": 0.02,
    "Mixx": 0,
    "Yahoo! Buzz": 0,
    "news.ycombinator.com": 0.01,
    "orkut": 0,
    "Other": 0
  },
  {
    "Date": "2015-09",
    "Facebook": 91.77,
    "YouTube": 0.48,
    "Twitter": 1.98,
    "Pinterest": 1.62,
    "Instagram": 0,
    "StumbleUpon": 1.01,
    "LinkedIn": 0.41,
    "Tumblr": 0.98,
    "Google+": 0.67,
    "NowPublic": 0,
    "reddit": 1.05,
    "Digg": 0,
    "Delicious": 0,
    "VKontakte": 0.02,
    "Mixx": 0,
    "Yahoo! Buzz": 0,
    "news.ycombinator.com": 0.01,
    "orkut": 0,
    "Other": 0
  },
  {
    "Date": "2015-10",
    "Facebook": 92.58,
    "YouTube": 0.22,
    "Twitter": 2.6,
    "Pinterest": 1.5,
    "Instagram": 0,
    "StumbleUpon": 0.77,
    "LinkedIn": 0.27,
    "Tumblr": 0.77,
    "Google+": 0.88,
    "NowPublic": 0,
    "reddit": 0.36,
    "Digg": 0,
    "Delicious": 0,
    "VKontakte": 0.02,
    "Mixx": 0,
    "Yahoo! Buzz": 0,
    "news.ycombinator.com": 0.01,
    "orkut": 0,
    "Other": 0.01
  },
  {
    "Date": "2015-11",
    "Facebook": 91.94,
    "YouTube": 0.19,
    "Twitter": 2.8,
    "Pinterest": 1.81,
    "Instagram": 0,
    "StumbleUpon": 0.87,
    "LinkedIn": 0.24,
    "Tumblr": 0.64,
    "Google+": 0.92,
    "NowPublic": 0,
    "reddit": 0.53,
    "Digg": 0,
    "Delicious": 0,
    "VKontakte": 0.03,
    "Mixx": 0,
    "Yahoo! Buzz": 0,
    "news.ycombinator.com": 0.02,
    "orkut": 0,
    "Other": 0
  },
  {
    "Date": "2015-12",
    "Facebook": 93.37,
    "YouTube": 0.22,
    "Twitter": 2.34,
    "Pinterest": 1.46,
    "Instagram": 0,
    "StumbleUpon": 0.61,
    "LinkedIn": 0.18,
    "Tumblr": 0.5,
    "Google+": 0.85,
    "NowPublic": 0,
    "reddit": 0.4,
    "Digg": 0,
    "Delicious": 0,
    "VKontakte": 0.04,
    "Mixx": 0,
    "Yahoo! Buzz": 0,
    "news.ycombinator.com": 0.02,
    "orkut": 0,
    "Other": 0
  },
  {
    "Date": "2016-01",
    "Facebook": 94.5,
    "YouTube": 0.2,
    "Twitter": 1.95,
    "Pinterest": 1.19,
    "Instagram": 0,
    "StumbleUpon": 0.47,
    "LinkedIn": 0.23,
    "Tumblr": 0.41,
    "Google+": 0.71,
    "NowPublic": 0,
    "reddit": 0.3,
    "Digg": 0,
    "Delicious": 0,
    "VKontakte": 0.03,
    "Mixx": 0,
    "Yahoo! Buzz": 0,
    "news.ycombinator.com": 0.01,
    "orkut": 0,
    "Other": 0
  },
  {
    "Date": "2016-02",
    "Facebook": 95.43,
    "YouTube": 0.05,
    "Twitter": 1.58,
    "Pinterest": 1.08,
    "Instagram": 0,
    "StumbleUpon": 0.43,
    "LinkedIn": 0.29,
    "Tumblr": 0.3,
    "Google+": 0.51,
    "NowPublic": 0,
    "reddit": 0.27,
    "Digg": 0,
    "Delicious": 0,
    "VKontakte": 0.03,
    "Mixx": 0,
    "Yahoo! Buzz": 0,
    "news.ycombinator.com": 0.01,
    "orkut": 0,
    "Other": 0
  },
  {
    "Date": "2016-03",
    "Facebook": 95.84,
    "YouTube": 0.04,
    "Twitter": 1.57,
    "Pinterest": 0.84,
    "Instagram": 0,
    "StumbleUpon": 0.37,
    "LinkedIn": 0.25,
    "Tumblr": 0.34,
    "Google+": 0.55,
    "NowPublic": 0,
    "reddit": 0.15,
    "Digg": 0,
    "Delicious": 0,
    "VKontakte": 0.04,
    "Mixx": 0,
    "Yahoo! Buzz": 0,
    "news.ycombinator.com": 0.01,
    "orkut": 0,
    "Other": 0
  },
  {
    "Date": "2016-04",
    "Facebook": 95.81,
    "YouTube": 0.06,
    "Twitter": 1.51,
    "Pinterest": 0.77,
    "Instagram": 0,
    "StumbleUpon": 0.32,
    "LinkedIn": 0.26,
    "Tumblr": 0.47,
    "Google+": 0.62,
    "NowPublic": 0,
    "reddit": 0.13,
    "Digg": 0,
    "Delicious": 0,
    "VKontakte": 0.04,
    "Mixx": 0,
    "Yahoo! Buzz": 0,
    "news.ycombinator.com": 0.01,
    "orkut": 0,
    "Other": 0
  },
  {
    "Date": "2016-05",
    "Facebook": 95.8,
    "YouTube": 0.05,
    "Twitter": 1.33,
    "Pinterest": 1.14,
    "Instagram": 0,
    "StumbleUpon": 0.3,
    "LinkedIn": 0.25,
    "Tumblr": 0.43,
    "Google+": 0.5,
    "NowPublic": 0,
    "reddit": 0.15,
    "Digg": 0,
    "Delicious": 0,
    "VKontakte": 0.05,
    "Mixx": 0,
    "Yahoo! Buzz": 0,
    "news.ycombinator.com": 0.01,
    "orkut": 0,
    "Other": 0
  },
  {
    "Date": "2016-06",
    "Facebook": 95.16,
    "YouTube": 0.12,
    "Twitter": 1.53,
    "Pinterest": 1.2,
    "Instagram": 0,
    "StumbleUpon": 0.27,
    "LinkedIn": 0.53,
    "Tumblr": 0.54,
    "Google+": 0.43,
    "NowPublic": 0,
    "reddit": 0.17,
    "Digg": 0,
    "Delicious": 0,
    "VKontakte": 0.03,
    "Mixx": 0,
    "Yahoo! Buzz": 0,
    "news.ycombinator.com": 0.01,
    "orkut": 0,
    "Other": 0
  },
  {
    "Date": "2016-07",
    "Facebook": 94.38,
    "YouTube": 0.04,
    "Twitter": 1.2,
    "Pinterest": 1.28,
    "Instagram": 0,
    "StumbleUpon": 0.28,
    "LinkedIn": 2.06,
    "Tumblr": 0.39,
    "Google+": 0.22,
    "NowPublic": 0,
    "reddit": 0.09,
    "Digg": 0,
    "Delicious": 0,
    "VKontakte": 0.03,
    "Mixx": 0,
    "Yahoo! Buzz": 0,
    "news.ycombinator.com": 0.01,
    "orkut": 0,
    "Other": 0.01
  },
  {
    "Date": "2016-08",
    "Facebook": 95.81,
    "YouTube": 0.03,
    "Twitter": 1.51,
    "Pinterest": 1.31,
    "Instagram": 0,
    "StumbleUpon": 0.26,
    "LinkedIn": 0.38,
    "Tumblr": 0.29,
    "Google+": 0.27,
    "NowPublic": 0,
    "reddit": 0.09,
    "Digg": 0,
    "Delicious": 0,
    "VKontakte": 0.03,
    "Mixx": 0,
    "Yahoo! Buzz": 0,
    "news.ycombinator.com": 0.01,
    "orkut": 0,
    "Other": 0.01
  },
  {
    "Date": "2016-09",
    "Facebook": 96.37,
    "YouTube": 0.02,
    "Twitter": 1.41,
    "Pinterest": 1.12,
    "Instagram": 0,
    "StumbleUpon": 0.22,
    "LinkedIn": 0.4,
    "Tumblr": 0.19,
    "Google+": 0.16,
    "NowPublic": 0,
    "reddit": 0.07,
    "Digg": 0,
    "Delicious": 0,
    "VKontakte": 0.02,
    "Mixx": 0,
    "Yahoo! Buzz": 0,
    "news.ycombinator.com": 0,
    "orkut": 0,
    "Other": 0
  },
  {
    "Date": "2016-10",
    "Facebook": 97.18,
    "YouTube": 0.04,
    "Twitter": 0.94,
    "Pinterest": 1.02,
    "Instagram": 0.04,
    "StumbleUpon": 0.16,
    "LinkedIn": 0.27,
    "Tumblr": 0.15,
    "Google+": 0.1,
    "NowPublic": 0,
    "reddit": 0.07,
    "Digg": 0,
    "Delicious": 0,
    "VKontakte": 0.02,
    "Mixx": 0,
    "Yahoo! Buzz": 0,
    "news.ycombinator.com": 0,
    "orkut": 0,
    "Other": 0.01
  },
  {
    "Date": "2016-11",
    "Facebook": 97.29,
    "YouTube": 0.05,
    "Twitter": 0.91,
    "Pinterest": 0.9,
    "Instagram": 0.12,
    "StumbleUpon": 0.17,
    "LinkedIn": 0.23,
    "Tumblr": 0.14,
    "Google+": 0.12,
    "NowPublic": 0,
    "reddit": 0.06,
    "Digg": 0,
    "Delicious": 0,
    "VKontakte": 0.01,
    "Mixx": 0,
    "Yahoo! Buzz": 0,
    "news.ycombinator.com": 0.01,
    "orkut": 0,
    "Other": 0
  },
  {
    "Date": "2016-12",
    "Facebook": 96.87,
    "YouTube": 0.05,
    "Twitter": 1.13,
    "Pinterest": 1.05,
    "Instagram": 0.18,
    "StumbleUpon": 0.16,
    "LinkedIn": 0.23,
    "Tumblr": 0.15,
    "Google+": 0.12,
    "NowPublic": 0,
    "reddit": 0.06,
    "Digg": 0,
    "Delicious": 0,
    "VKontakte": 0,
    "Mixx": 0,
    "Yahoo! Buzz": 0,
    "news.ycombinator.com": 0,
    "orkut": 0,
    "Other": 0
  },
  {
    "Date": "2017-01",
    "Facebook": 96.64,
    "YouTube": 0.05,
    "Twitter": 1.14,
    "Pinterest": 1.3,
    "Instagram": 0.13,
    "StumbleUpon": 0.17,
    "LinkedIn": 0.21,
    "Tumblr": 0.15,
    "Google+": 0.13,
    "NowPublic": 0,
    "reddit": 0.06,
    "Digg": 0,
    "Delicious": 0,
    "VKontakte": 0.01,
    "Mixx": 0,
    "Yahoo! Buzz": 0,
    "news.ycombinator.com": 0.01,
    "orkut": 0,
    "Other": 0
  },
  {
    "Date": "2017-02",
    "Facebook": 96.79,
    "YouTube": 0.04,
    "Twitter": 1.04,
    "Pinterest": 1.33,
    "Instagram": 0.12,
    "StumbleUpon": 0.16,
    "LinkedIn": 0.19,
    "Tumblr": 0.13,
    "Google+": 0.1,
    "NowPublic": 0,
    "reddit": 0.07,
    "Digg": 0,
    "Delicious": 0,
    "VKontakte": 0.03,
    "Mixx": 0,
    "Yahoo! Buzz": 0,
    "news.ycombinator.com": 0.01,
    "orkut": 0,
    "Other": 0
  },
  {
    "Date": "2017-03",
    "Facebook": 96.27,
    "YouTube": 0.05,
    "Twitter": 1.22,
    "Pinterest": 1.54,
    "Instagram": 0.18,
    "StumbleUpon": 0.17,
    "LinkedIn": 0.19,
    "Tumblr": 0.14,
    "Google+": 0.12,
    "NowPublic": 0,
    "reddit": 0.08,
    "Digg": 0,
    "Delicious": 0,
    "VKontakte": 0.02,
    "Mixx": 0,
    "Yahoo! Buzz": 0,
    "news.ycombinator.com": 0.01,
    "orkut": 0,
    "Other": 0
  },
  {
    "Date": "2017-04",
    "Facebook": 95.86,
    "YouTube": 0.12,
    "Twitter": 1.4,
    "Pinterest": 1.52,
    "Instagram": 0.28,
    "StumbleUpon": 0.25,
    "LinkedIn": 0.15,
    "Tumblr": 0.12,
    "Google+": 0.12,
    "NowPublic": 0,
    "reddit": 0.15,
    "Digg": 0,
    "Delicious": 0,
    "VKontakte": 0.03,
    "Mixx": 0,
    "Yahoo! Buzz": 0,
    "news.ycombinator.com": 0.01,
    "orkut": 0,
    "Other": 0
  },
  {
    "Date": "2017-05",
    "Facebook": 96.37,
    "YouTube": 0.71,
    "Twitter": 1.27,
    "Pinterest": 0.76,
    "Instagram": 0.19,
    "StumbleUpon": 0.2,
    "LinkedIn": 0.19,
    "Tumblr": 0.08,
    "Google+": 0.13,
    "NowPublic": 0,
    "reddit": 0.07,
    "Digg": 0,
    "Delicious": 0,
    "VKontakte": 0.02,
    "Mixx": 0,
    "Yahoo! Buzz": 0,
    "news.ycombinator.com": 0,
    "orkut": 0,
    "Other": 0
  },
  {
    "Date": "2017-06",
    "Facebook": 94.3,
    "YouTube": 1.33,
    "Twitter": 1.49,
    "Pinterest": 1.57,
    "Instagram": 0.38,
    "StumbleUpon": 0.21,
    "LinkedIn": 0.36,
    "Tumblr": 0.1,
    "Google+": 0.16,
    "NowPublic": 0,
    "reddit": 0.07,
    "Digg": 0,
    "Delicious": 0,
    "VKontakte": 0.01,
    "Mixx": 0,
    "Yahoo! Buzz": 0,
    "news.ycombinator.com": 0.01,
    "orkut": 0,
    "Other": 0.01
  },
  {
    "Date": "2017-07",
    "Facebook": 93.36,
    "YouTube": 2.04,
    "Twitter": 1.38,
    "Pinterest": 1.73,
    "Instagram": 0.73,
    "StumbleUpon": 0.2,
    "LinkedIn": 0.21,
    "Tumblr": 0.11,
    "Google+": 0.14,
    "NowPublic": 0,
    "reddit": 0.07,
    "Digg": 0,
    "Delicious": 0,
    "VKontakte": 0.01,
    "Mixx": 0,
    "Yahoo! Buzz": 0,
    "news.ycombinator.com": 0.01,
    "orkut": 0,
    "Other": 0
  },
  {
    "Date": "2017-08",
    "Facebook": 90.36,
    "YouTube": 3.33,
    "Twitter": 1.23,
    "Pinterest": 1.82,
    "Instagram": 2.54,
    "StumbleUpon": 0.2,
    "LinkedIn": 0.18,
    "Tumblr": 0.09,
    "Google+": 0.13,
    "NowPublic": 0,
    "reddit": 0.11,
    "Digg": 0,
    "Delicious": 0,
    "VKontakte": 0.01,
    "Mixx": 0,
    "Yahoo! Buzz": 0,
    "news.ycombinator.com": 0,
    "orkut": 0,
    "Other": 0
  },
  {
    "Date": "2017-09",
    "Facebook": 91.21,
    "YouTube": 2.14,
    "Twitter": 1.57,
    "Pinterest": 2.23,
    "Instagram": 1.97,
    "StumbleUpon": 0.25,
    "LinkedIn": 0.22,
    "Tumblr": 0.09,
    "Google+": 0.16,
    "NowPublic": 0,
    "reddit": 0.15,
    "Digg": 0,
    "Delicious": 0,
    "VKontakte": 0,
    "Mixx": 0,
    "Yahoo! Buzz": 0,
    "news.ycombinator.com": 0.01,
    "orkut": 0,
    "Other": 0
  },
  {
    "Date": "2017-10",
    "Facebook": 88.38,
    "YouTube": 1.97,
    "Twitter": 3.53,
    "Pinterest": 2.05,
    "Instagram": 3.28,
    "StumbleUpon": 0.2,
    "LinkedIn": 0.22,
    "Tumblr": 0.08,
    "Google+": 0.16,
    "NowPublic": 0,
    "reddit": 0.12,
    "Digg": 0,
    "Delicious": 0,
    "VKontakte": 0,
    "Mixx": 0,
    "Yahoo! Buzz": 0,
    "news.ycombinator.com": 0.01,
    "orkut": 0,
    "Other": 0
  },
  {
    "Date": "2017-11",
    "Facebook": 86.37,
    "YouTube": 5.64,
    "Twitter": 2,
    "Pinterest": 1.59,
    "Instagram": 3.76,
    "StumbleUpon": 0.15,
    "LinkedIn": 0.24,
    "Tumblr": 0.06,
    "Google+": 0.09,
    "NowPublic": 0,
    "reddit": 0.09,
    "Digg": 0,
    "Delicious": 0,
    "VKontakte": 0,
    "Mixx": 0,
    "Yahoo! Buzz": 0,
    "news.ycombinator.com": 0.01,
    "orkut": 0,
    "Other": 0
  },
  {
    "Date": "2017-12",
    "Facebook": 85.02,
    "YouTube": 6.82,
    "Twitter": 1.21,
    "Pinterest": 1.62,
    "Instagram": 4.78,
    "StumbleUpon": 0.11,
    "LinkedIn": 0.19,
    "Tumblr": 0.06,
    "Google+": 0.08,
    "NowPublic": 0,
    "reddit": 0.11,
    "Digg": 0,
    "Delicious": 0,
    "VKontakte": 0.01,
    "Mixx": 0,
    "Yahoo! Buzz": 0,
    "news.ycombinator.com": 0,
    "orkut": 0,
    "Other": 0
  },
  {
    "Date": "2018-01",
    "Facebook": 85.3,
    "YouTube": 6.73,
    "Twitter": 1.09,
    "Pinterest": 1.64,
    "Instagram": 4.8,
    "StumbleUpon": 0.12,
    "LinkedIn": 0.12,
    "Tumblr": 0.05,
    "Google+": 0.07,
    "NowPublic": 0,
    "reddit": 0.06,
    "Digg": 0,
    "Delicious": 0,
    "VKontakte": 0.02,
    "Mixx": 0,
    "Yahoo! Buzz": 0,
    "news.ycombinator.com": 0.01,
    "orkut": 0,
    "Other": 0
  },
  {
    "Date": "2018-02",
    "Facebook": 82.98,
    "YouTube": 9.15,
    "Twitter": 1.26,
    "Pinterest": 1.89,
    "Instagram": 4.2,
    "StumbleUpon": 0.16,
    "LinkedIn": 0.14,
    "Tumblr": 0.07,
    "Google+": 0.09,
    "NowPublic": 0,
    "reddit": 0.06,
    "Digg": 0,
    "Delicious": 0,
    "VKontakte": 0,
    "Mixx": 0,
    "Yahoo! Buzz": 0,
    "news.ycombinator.com": 0,
    "orkut": 0,
    "Other": 0
  },
  {
    "Date": "2018-03",
    "Facebook": 81.52,
    "YouTube": 9.38,
    "Twitter": 1.13,
    "Pinterest": 1.74,
    "Instagram": 5.66,
    "StumbleUpon": 0.16,
    "LinkedIn": 0.17,
    "Tumblr": 0.07,
    "Google+": 0.11,
    "NowPublic": 0,
    "reddit": 0.06,
    "Digg": 0,
    "Delicious": 0,
    "VKontakte": 0,
    "Mixx": 0,
    "Yahoo! Buzz": 0,
    "news.ycombinator.com": 0.01,
    "orkut": 0,
    "Other": 0
  },
  {
    "Date": "2018-04",
    "Facebook": 83.49,
    "YouTube": 9.7,
    "Twitter": 1.34,
    "Pinterest": 2.43,
    "Instagram": 2.33,
    "StumbleUpon": 0.16,
    "LinkedIn": 0.25,
    "Tumblr": 0.07,
    "Google+": 0.14,
    "NowPublic": 0,
    "reddit": 0.07,
    "Digg": 0,
    "Delicious": 0,
    "VKontakte": 0.01,
    "Mixx": 0,
    "Yahoo! Buzz": 0,
    "news.ycombinator.com": 0,
    "orkut": 0,
    "Other": 0
  },
  {
    "Date": "2018-05",
    "Facebook": 84.2,
    "YouTube": 9.34,
    "Twitter": 1.12,
    "Pinterest": 2.61,
    "Instagram": 1.97,
    "StumbleUpon": 0.15,
    "LinkedIn": 0.28,
    "Tumblr": 0.08,
    "Google+": 0.15,
    "NowPublic": 0,
    "reddit": 0.06,
    "Digg": 0,
    "Delicious": 0,
    "VKontakte": 0.02,
    "Mixx": 0,
    "Yahoo! Buzz": 0,
    "news.ycombinator.com": 0.01,
    "orkut": 0,
    "Other": 0
  },
  {
    "Date": "2018-06",
    "Facebook": 77.2,
    "YouTube": 12.63,
    "Twitter": 1.84,
    "Pinterest": 3.71,
    "Instagram": 3.61,
    "StumbleUpon": 0.14,
    "LinkedIn": 0.4,
    "Tumblr": 0.15,
    "Google+": 0.18,
    "NowPublic": 0,
    "reddit": 0.06,
    "Digg": 0,
    "Delicious": 0,
    "VKontakte": 0.07,
    "Mixx": 0,
    "Yahoo! Buzz": 0,
    "news.ycombinator.com": 0,
    "orkut": 0,
    "Other": 0
  },
  {
    "Date": "2018-07",
    "Facebook": 77.08,
    "YouTube": 11.11,
    "Twitter": 2.14,
    "Pinterest": 3.92,
    "Instagram": 4.95,
    "StumbleUpon": 0.08,
    "LinkedIn": 0.27,
    "Tumblr": 0.1,
    "Google+": 0.18,
    "NowPublic": 0,
    "reddit": 0.07,
    "Digg": 0,
    "Delicious": 0,
    "VKontakte": 0.09,
    "Mixx": 0,
    "Yahoo! Buzz": 0,
    "news.ycombinator.com": 0.01,
    "orkut": 0,
    "Other": 0
  },
  {
    "Date": "2018-08",
    "Facebook": 76.87,
    "YouTube": 10.8,
    "Twitter": 1.97,
    "Pinterest": 4.3,
    "Instagram": 5.36,
    "StumbleUpon": 0,
    "LinkedIn": 0.23,
    "Tumblr": 0.09,
    "Google+": 0.19,
    "NowPublic": 0,
    "reddit": 0.09,
    "Digg": 0,
    "Delicious": 0,
    "VKontakte": 0.08,
    "Mixx": 0,
    "Yahoo! Buzz": 0,
    "news.ycombinator.com": 0.01,
    "orkut": 0,
    "Other": 0
  },
  {
    "Date": "2018-09",
    "Facebook": 83.83,
    "YouTube": 7.48,
    "Twitter": 1.44,
    "Pinterest": 2.68,
    "Instagram": 4.11,
    "StumbleUpon": 0,
    "LinkedIn": 0.11,
    "Tumblr": 0.15,
    "Google+": 0.11,
    "NowPublic": 0,
    "reddit": 0.06,
    "Digg": 0,
    "Delicious": 0,
    "VKontakte": 0.03,
    "Mixx": 0,
    "Yahoo! Buzz": 0,
    "news.ycombinator.com": 0,
    "orkut": 0,
    "Other": 0
  },
  {
    "Date": "2018-10",
    "Facebook": 86.56,
    "YouTube": 5.22,
    "Twitter": 1.04,
    "Pinterest": 2.01,
    "Instagram": 4.79,
    "StumbleUpon": 0,
    "LinkedIn": 0.07,
    "Tumblr": 0.1,
    "Google+": 0.12,
    "NowPublic": 0,
    "reddit": 0.06,
    "Digg": 0,
    "Delicious": 0,
    "VKontakte": 0.03,
    "Mixx": 0,
    "Yahoo! Buzz": 0,
    "news.ycombinator.com": 0,
    "orkut": 0,
    "Other": 0
  },
  {
    "Date": "2018-11",
    "Facebook": 88.23,
    "YouTube": 5.08,
    "Twitter": 1.2,
    "Pinterest": 2.14,
    "Instagram": 2.93,
    "StumbleUpon": 0.01,
    "LinkedIn": 0.08,
    "Tumblr": 0.08,
    "Google+": 0.15,
    "NowPublic": 0,
    "reddit": 0.08,
    "Digg": 0,
    "Delicious": 0,
    "VKontakte": 0.02,
    "Mixx": 0,
    "Yahoo! Buzz": 0,
    "news.ycombinator.com": 0,
    "orkut": 0,
    "Other": 0
  },
  {
    "Date": "2018-12",
    "Facebook": 89.28,
    "YouTube": 3.58,
    "Twitter": 1.56,
    "Pinterest": 2.68,
    "Instagram": 2.34,
    "StumbleUpon": 0.01,
    "LinkedIn": 0.1,
    "Tumblr": 0.08,
    "Google+": 0.22,
    "NowPublic": 0,
    "reddit": 0.12,
    "Digg": 0,
    "Delicious": 0,
    "VKontakte": 0.03,
    "Mixx": 0,
    "Yahoo! Buzz": 0,
    "news.ycombinator.com": 0,
    "orkut": 0,
    "Other": 0
  },
  {
    "Date": "2019-01",
    "Facebook": 90.45,
    "YouTube": 2.53,
    "Twitter": 1.75,
    "Pinterest": 2.95,
    "Instagram": 1.77,
    "StumbleUpon": 0,
    "LinkedIn": 0.11,
    "Tumblr": 0.06,
    "Google+": 0.18,
    "NowPublic": 0,
    "reddit": 0.17,
    "Digg": 0,
    "Delicious": 0,
    "VKontakte": 0.03,
    "Mixx": 0,
    "Yahoo! Buzz": 0,
    "news.ycombinator.com": 0,
    "orkut": 0,
    "Other": 0
  },
  {
    "Date": "2019-02",
    "Facebook": 91.97,
    "YouTube": 1.93,
    "Twitter": 1.42,
    "Pinterest": 2.76,
    "Instagram": 1.66,
    "StumbleUpon": 0,
    "LinkedIn": 0.09,
    "Tumblr": 0.04,
    "Google+": 0.06,
    "NowPublic": 0,
    "reddit": 0.06,
    "Digg": 0,
    "Delicious": 0,
    "VKontakte": 0.01,
    "Mixx": 0,
    "Yahoo! Buzz": 0,
    "news.ycombinator.com": 0.01,
    "orkut": 0,
    "Other": 0
  },
  {
    "Date": "2019-03",
    "Facebook": 90.29,
    "YouTube": 2.32,
    "Twitter": 1.41,
    "Pinterest": 3.33,
    "Instagram": 2.41,
    "StumbleUpon": 0,
    "LinkedIn": 0.08,
    "Tumblr": 0.05,
    "Google+": 0.04,
    "NowPublic": 0,
    "reddit": 0.05,
    "Digg": 0,
    "Delicious": 0,
    "VKontakte": 0.02,
    "Mixx": 0,
    "Yahoo! Buzz": 0,
    "news.ycombinator.com": 0,
    "orkut": 0,
    "Other": 0
  },
  {
    "Date": "2019-04",
    "Facebook": 87.62,
    "YouTube": 3.25,
    "Twitter": 1.76,
    "Pinterest": 4.26,
    "Instagram": 2.82,
    "StumbleUpon": 0.01,
    "LinkedIn": 0.13,
    "Tumblr": 0.05,
    "Google+": 0.01,
    "NowPublic": 0,
    "reddit": 0.06,
    "Digg": 0,
    "Delicious": 0,
    "VKontakte": 0.03,
    "Mixx": 0,
    "Yahoo! Buzz": 0,
    "news.ycombinator.com": 0.01,
    "orkut": 0,
    "Other": 0
  },
  {
    "Date": "2019-05",
    "Facebook": 91,
    "YouTube": 2.47,
    "Twitter": 1.25,
    "Pinterest": 3.37,
    "Instagram": 1.67,
    "StumbleUpon": 0,
    "LinkedIn": 0.12,
    "Tumblr": 0.04,
    "Google+": 0,
    "NowPublic": 0,
    "reddit": 0.05,
    "Digg": 0,
    "Delicious": 0,
    "VKontakte": 0.03,
    "Mixx": 0,
    "Yahoo! Buzz": 0,
    "news.ycombinator.com": 0,
    "orkut": 0,
    "Other": 0
  },
  {
    "Date": "2019-06",
    "Facebook": 90.36,
    "YouTube": 2.38,
    "Twitter": 2.16,
    "Pinterest": 3.7,
    "Instagram": 1.17,
    "StumbleUpon": 0,
    "LinkedIn": 0.1,
    "Tumblr": 0.04,
    "Google+": 0,
    "NowPublic": 0,
    "reddit": 0.05,
    "Digg": 0,
    "Delicious": 0,
    "VKontakte": 0.03,
    "Mixx": 0,
    "Yahoo! Buzz": 0,
    "news.ycombinator.com": 0,
    "orkut": 0,
    "Other": 0
  },
  {
    "Date": "2019-07",
    "Facebook": 89.29,
    "YouTube": 2.99,
    "Twitter": 1.95,
    "Pinterest": 4.04,
    "Instagram": 1.49,
    "StumbleUpon": 0,
    "LinkedIn": 0.08,
    "Tumblr": 0.05,
    "Google+": 0,
    "NowPublic": 0,
    "reddit": 0.07,
    "Digg": 0,
    "Delicious": 0,
    "VKontakte": 0.03,
    "Mixx": 0,
    "Yahoo! Buzz": 0,
    "news.ycombinator.com": 0,
    "orkut": 0,
    "Other": 0
  },
  {
    "Date": "2019-08",
    "Facebook": 89.79,
    "YouTube": 3.11,
    "Twitter": 1.79,
    "Pinterest": 3.68,
    "Instagram": 1.41,
    "StumbleUpon": 0,
    "LinkedIn": 0.07,
    "Tumblr": 0.04,
    "Google+": 0,
    "NowPublic": 0,
    "reddit": 0.06,
    "Digg": 0,
    "Delicious": 0,
    "VKontakte": 0.03,
    "Mixx": 0,
    "Yahoo! Buzz": 0,
    "news.ycombinator.com": 0,
    "orkut": 0,
    "Other": 0
  },
  {
    "Date": "2019-09",
    "Facebook": 88.05,
    "YouTube": 3.65,
    "Twitter": 1.82,
    "Pinterest": 3.78,
    "Instagram": 2.44,
    "StumbleUpon": 0,
    "LinkedIn": 0.09,
    "Tumblr": 0.04,
    "Google+": 0,
    "NowPublic": 0,
    "reddit": 0.09,
    "Digg": 0,
    "Delicious": 0,
    "VKontakte": 0.03,
    "Mixx": 0,
    "Yahoo! Buzz": 0,
    "news.ycombinator.com": 0.01,
    "orkut": 0,
    "Other": 0
  },
  {
    "Date": "2019-10",
    "Facebook": 83.8,
    "YouTube": 4.59,
    "Twitter": 2.84,
    "Pinterest": 3.83,
    "Instagram": 4.69,
    "StumbleUpon": 0,
    "LinkedIn": 0.08,
    "Tumblr": 0.04,
    "Google+": 0,
    "NowPublic": 0,
    "reddit": 0.07,
    "Digg": 0,
    "Delicious": 0,
    "VKontakte": 0.05,
    "Mixx": 0,
    "Yahoo! Buzz": 0,
    "news.ycombinator.com": 0.01,
    "orkut": 0,
    "Other": 0
  },
  {
    "Date": "2019-11",
    "Facebook": 84.68,
    "YouTube": 4.06,
    "Twitter": 2.3,
    "Pinterest": 3.85,
    "Instagram": 4.84,
    "StumbleUpon": 0,
    "LinkedIn": 0.08,
    "Tumblr": 0.04,
    "Google+": 0,
    "NowPublic": 0,
    "reddit": 0.06,
    "Digg": 0,
    "Delicious": 0,
    "VKontakte": 0.08,
    "Mixx": 0,
    "Yahoo! Buzz": 0,
    "news.ycombinator.com": 0,
    "orkut": 0,
    "Other": 0
  },
  {
    "Date": "2019-12",
    "Facebook": 82.53,
    "YouTube": 6.66,
    "Twitter": 1.79,
    "Pinterest": 3.76,
    "Instagram": 5.03,
    "StumbleUpon": 0,
    "LinkedIn": 0.06,
    "Tumblr": 0.03,
    "Google+": 0,
    "NowPublic": 0,
    "reddit": 0.05,
    "Digg": 0,
    "Delicious": 0,
    "VKontakte": 0.07,
    "Mixx": 0,
    "Yahoo! Buzz": 0,
    "news.ycombinator.com": 0,
    "orkut": 0,
    "Other": 0
  },
  {
    "Date": "2020-01",
    "Facebook": 83.56,
    "YouTube": 3.39,
    "Twitter": 2.23,
    "Pinterest": 4.08,
    "Instagram": 6.51,
    "StumbleUpon": 0,
    "LinkedIn": 0.06,
    "Tumblr": 0.04,
    "Google+": 0,
    "NowPublic": 0,
    "reddit": 0.06,
    "Digg": 0,
    "Delicious": 0,
    "VKontakte": 0.07,
    "Mixx": 0,
    "Yahoo! Buzz": 0,
    "news.ycombinator.com": 0.01,
    "orkut": 0,
    "Other": 0
  },
  {
    "Date": "2020-02",
    "Facebook": 82.11,
    "YouTube": 2.64,
    "Twitter": 2.43,
    "Pinterest": 4.59,
    "Instagram": 7.94,
    "StumbleUpon": 0,
    "LinkedIn": 0.07,
    "Tumblr": 0.05,
    "Google+": 0,
    "NowPublic": 0,
    "reddit": 0.08,
    "Digg": 0,
    "Delicious": 0,
    "VKontakte": 0.08,
    "Mixx": 0,
    "Yahoo! Buzz": 0,
    "news.ycombinator.com": 0,
    "orkut": 0,
    "Other": 0
  },
  {
    "Date": "2020-03",
    "Facebook": 84.94,
    "YouTube": 2.61,
    "Twitter": 2.58,
    "Pinterest": 3.35,
    "Instagram": 6.32,
    "StumbleUpon": 0,
    "LinkedIn": 0.07,
    "Tumblr": 0.03,
    "Google+": 0,
    "NowPublic": 0,
    "reddit": 0.06,
    "Digg": 0,
    "Delicious": 0,
    "VKontakte": 0.04,
    "Mixx": 0,
    "Yahoo! Buzz": 0,
    "news.ycombinator.com": 0,
    "orkut": 0,
    "Other": 0
  },
  {
    "Date": "2020-04",
    "Facebook": 86.04,
    "YouTube": 3.26,
    "Twitter": 2.57,
    "Pinterest": 3,
    "Instagram": 4.84,
    "StumbleUpon": 0,
    "LinkedIn": 0.07,
    "Tumblr": 0.04,
    "Google+": 0,
    "NowPublic": 0,
    "reddit": 0.15,
    "Digg": 0,
    "Delicious": 0,
    "VKontakte": 0.03,
    "Mixx": 0,
    "Yahoo! Buzz": 0,
    "news.ycombinator.com": 0,
    "orkut": 0,
    "Other": 0
  },
  {
    "Date": "2020-05",
    "Facebook": 90.06,
    "YouTube": 3.18,
    "Twitter": 1.28,
    "Pinterest": 2.9,
    "Instagram": 2.34,
    "StumbleUpon": 0,
    "LinkedIn": 0.08,
    "Tumblr": 0.05,
    "Google+": 0,
    "NowPublic": 0,
    "reddit": 0.08,
    "Digg": 0,
    "Delicious": 0,
    "VKontakte": 0.03,
    "Mixx": 0,
    "Yahoo! Buzz": 0,
    "news.ycombinator.com": 0.01,
    "orkut": 0,
    "Other": 0
  },
  {
    "Date": "2020-06",
    "Facebook": 89.45,
    "YouTube": 3.2,
    "Twitter": 2.19,
    "Pinterest": 2.73,
    "Instagram": 2.21,
    "StumbleUpon": 0,
    "LinkedIn": 0.08,
    "Tumblr": 0.06,
    "Google+": 0,
    "NowPublic": 0,
    "reddit": 0.06,
    "Digg": 0,
    "Delicious": 0,
    "VKontakte": 0.01,
    "Mixx": 0,
    "Yahoo! Buzz": 0,
    "news.ycombinator.com": 0.01,
    "orkut": 0,
    "Other": 0
  },
  {
    "Date": "2009-03",
    "Facebook": 0,
    "YouTube": 0,
    "Twitter": 0,
    "Pinterest": 0,
    "Instagram": 0,
    "StumbleUpon": 0,
    "LinkedIn": 0,
    "Tumblr": 0,
    "Google+": 0,
    "NowPublic": 0,
    "reddit": 0,
    "Digg": 0,
    "Delicious": 0,
    "VKontakte": 0,
    "Mixx": 0,
    "Yahoo! Buzz": 0,
    "news.ycombinator.com": 0,
    "orkut": 0,
    "Other": 0
  }
]